arcade_outlook_calendar/__init__.py
arcade_outlook_calendar/_utils.py
arcade_outlook_calendar/client.py
arcade_outlook_calendar/constants.py
arcade_outlook_calendar/models.py
arcade_outlook_calendar/who_am_i_util.py
arcade_outlook_calendar/tools/__init__.py
arcade_outlook_calendar/tools/create_event.py
arcade_outlook_calendar/tools/get_event.py
arcade_outlook_calendar/tools/list_events_in_time_range.py
arcade_outlook_calendar/tools/system_context.py
arcade_outlook_calendar-2.2.1.dist-info/METADATA
arcade_outlook_calendar-2.2.1.dist-info/WHEEL
arcade_outlook_calendar-2.2.1.dist-info/licenses/LICENSE
arcade_outlook_calendar-2.2.1.dist-info/RECORD
